{
    "@context": "http://schema.org",
    "itemListElement": [
        {
            "position": 1,
            "@type": "ListItem",
            "item": {
                "@id": "/c/rockton-il-us/food",
                "name": "Food"
            }
        },
        {
            "position": 2,
            "@type": "ListItem",
            "item": {
                "@id": "/c/rockton-il-us/gourmet",
                "name": "Specialty Food"
            }
        },
        {
            "position": 3,
            "@type": "ListItem",
            "item": {
                "@id": "/c/rockton-il-us/markets",
                "name": "Fruits & Veggies"
            }
        }
    ],
    "@type": "BreadcrumbList"
}